{
  "addons": {
    "coolPhotonTheme@zapsnh": {
      "updates": [
        {
          "version": "0.23.3",
          "update_link": "https://github.com/zapSNH/zcpt-webextension/releases/download/v0.23.3/zapsCoolPhotonTheme-esr.xpi",
          "applications": {
            "gecko": {
                "strict_min_version": "115.0",
                "strict_max_version": "115.*"
            }
          }
        },
        {
          "version": "0.23.3.1",
          "update_link": "https://github.com/zapSNH/zcpt-webextension/releases/download/v0.23.3/zapsCoolPhotonTheme.xpi",
          "applications": {
            "gecko": {
                "strict_min_version": "116.0"
            }
          }
        }
      ]
    }
  }
}
